[
    {
        "key": "https://www.instagram.com/p/B5eaoIQHk6P/",
        "datetime": "2019-11-30T03:55:36.000Z",
        "img_urls": [
            "https://scontent-ort2-1.cdninstagram.com/v/t51.2885-15/e35/p1080x1080/73455926_211217419892745_3394939006212748247_n.jpg?_nc_ht=scontent-ort2-1.cdninstagram.com&_nc_cat=1&oh=5dfb38a5a611fac463d361cbfb3a3338&oe=5E88C57C"
        ],
        "likes": 461482,
        "caption": "20% off the entire site right now. @kylieskin KylieSkin.com #BlackFriday",
        "hashtags": [
            "BlackFriday"
        ]
    },
    {
        "key": "https://www.instagram.com/p/B5eA1coHusj/",
        "datetime": "2019-11-30T00:10:13.000Z",
        "img_urls": [
            "https://scontent-ort2-1.cdninstagram.com/v/t51.2885-15/e35/p1080x1080/71015121_416542195897367_4449473111054543738_n.jpg?_nc_ht=scontent-ort2-1.cdninstagram.com&_nc_cat=1&oh=c9b8bf0914da6fe5d785007ce8dfd561&oe=5E70CCB4",
            "https://scontent-ort2-1.cdninstagram.com/v/t51.2885-15/e35/p1080x1080/70579650_2517918291663389_3311780019649105950_n.jpg?_nc_ht=scontent-ort2-1.cdninstagram.com&_nc_cat=1&oh=b9fff834ff6e471152182c9fd9d9b836&oe=5E80B135",
            "https://scontent-ort2-1.cdninstagram.com/v/t51.2885-15/e35/p1080x1080/74673909_2884048781640326_6073859781546721997_n.jpg?_nc_ht=scontent-ort2-1.cdninstagram.com&_nc_cat=1&oh=df47c1b46da5556833204ef8f6662c1c&oe=5E6BA355"
        ],
        "likes": 3629721,
        "caption": "thankful"
    },
    {
        "key": "https://www.instagram.com/p/B5ddxzGnU6n/",
        "datetime": "2019-11-29T19:03:53.000Z",
        "img_urls": [
            "https://scontent-ort2-1.cdninstagram.com/v/t51.2885-15/e35/s1080x1080/75244433_1654396214696770_4588703350470055029_n.jpg?_nc_ht=scontent-ort2-1.cdninstagram.com&_nc_cat=1&oh=4cacf0a2a1849f9424f6f4ae42a4739e&oe=5E6AC033"
        ],
        "likes": 968406,
        "caption": "happy Black Friday! Shop my biggest sale of the year! Up to 40% off at KylieCosmetics.com and @ultabeauty, and 20% off at KylieSkin.com 💕 #BlackFriday",
        "hashtags": [
            "BlackFriday"
        ]
    },
    {
        "key": "https://www.instagram.com/p/B5bccR_nSjK/",
        "datetime": "2019-11-29T00:13:44.000Z",
        "img_urls": [
            "https://scontent-ort2-1.cdninstagram.com/v/t51.2885-15/e35/s1080x1080/79372043_156287065743573_4612488777785153434_n.jpg?_nc_ht=scontent-ort2-1.cdninstagram.com&_nc_cat=1&oh=3a301676fa2f33390f5fe52d563b0560&oe=5E669A69",
            "https://scontent-ort2-1.cdninstagram.com/v/t51.2885-15/e35/s1080x1080/69055960_108327143842041_1622964540782402260_n.jpg?_nc_ht=scontent-ort2-1.cdninstagram.com&_nc_cat=1&oh=5677dd04f6dbd329067f774024630521&oe=5E74BDDC",
            "https://scontent-ort2-1.cdninstagram.com/v/t51.2885-15/e35/s1080x1080/75562945_242106283435441_3263544518158953791_n.jpg?_nc_ht=scontent-ort2-1.cdninstagram.com&_nc_cat=1&oh=c349b90760dd1d839f490af264e18804&oe=5E6E8757"
        ],
        "likes": 1130012,
        "caption": "my @kylieskin #BlackFriday sale starts now! Go to KylieSkin.com 💕",
        "hashtags": [
            "BlackFriday"
        ]
    },
    {
        "key": "https://www.instagram.com/p/B5a0T9_H_FR/",
        "datetime": "2019-11-28T18:23:04.000Z",
        "img_urls": [
            "https://scontent-ort2-1.cdninstagram.com/v/t51.2885-15/e35/p1080x1080/72195056_542030386577601_1248251985572870142_n.jpg?_nc_ht=scontent-ort2-1.cdninstagram.com&_nc_cat=1&oh=5a52a081d63fb79472405d220ec99582&oe=5E868FC3"
        ],
        "likes": 598519,
        "caption": "introducing my new Candy K sets! I turned my iconic lip kit shade into a complete kit, with a matte bullet lipstick, velvet liquid lipstick, lip liner, blush and highlighter duo and eyeshadow duo! Can’t wait for you guys to get these ❤️ launching today at 5pm pst, same time as my @kyliecosmetics #BlackFriday sale! 40% off lips and 30% off eyes and face at KylieCosmetics.com 😘",
        "hashtags": [
            "BlackFriday"
        ]
    },
    {
        "key": "https://www.instagram.com/p/B5YzjVsn_k9/",
        "datetime": "2019-11-27T23:40:33.000Z",
        "img_urls": [
            "https://scontent-ort2-1.cdninstagram.com/v/t51.2885-15/e35/72963221_2477344699206079_6325191412088756820_n.jpg?_nc_ht=scontent-ort2-1.cdninstagram.com&_nc_cat=1&oh=9632a19d07df0722a138d722cd8157b5&oe=5DE506E4"
        ],
        "views": 1827071,
        "likes": 348387,
        "caption": "It’s almost #BlackFriday! For @kyliecosmetics it’s 40% off all lips and 30% off face and eyes at KylieCosmetics.com and @ultabeauty starting 5pm pst tomorrow! Then for @kylieskin it’s 20% off sitewide at KylieSkin.com starting at 4pm pst, plus I’m restocking my sets and launching my new slides! 😍 🖤",
        "hashtags": [
            "BlackFriday"
        ]
    },
    {
        "key": "https://www.instagram.com/p/B5YoQv3HwPp/",
        "datetime": "2019-11-27T21:59:18.000Z",
        "img_urls": [
            "https://scontent-ort2-1.cdninstagram.com/v/t51.2885-15/e35/p1080x1080/72777584_195001288204934_7799280645039448725_n.jpg?_nc_ht=scontent-ort2-1.cdninstagram.com&_nc_cat=1&oh=3a708228a82be986d3ab65406ace53d4&oe=5E89842A",
            "https://scontent-ort2-1.cdninstagram.com/v/t51.2885-15/e35/p1080x1080/75294317_776458136509306_765524093448445918_n.jpg?_nc_ht=scontent-ort2-1.cdninstagram.com&_nc_cat=1&oh=273f610c090bd4d5cd19dae4089c03a8&oe=5E83491E",
            "https://scontent-ort2-1.cdninstagram.com/v/t51.2885-15/e35/p1080x1080/73315831_2138852016216302_415024732532357519_n.jpg?_nc_ht=scontent-ort2-1.cdninstagram.com&_nc_cat=1&oh=045eed9438265a1ea11a6435d08768a2&oe=5E79E603",
            "https://scontent-ort2-1.cdninstagram.com/v/t51.2885-15/e35/p1080x1080/79256257_151649039525954_386295322581164322_n.jpg?_nc_ht=scontent-ort2-1.cdninstagram.com&_nc_cat=1&oh=c78bfc252aef386166776d48fa3bfc68&oe=5E877C8C",
            "https://scontent-ort2-1.cdninstagram.com/v/t51.2885-15/e35/p1080x1080/79484889_2523891277830621_1119820813312365361_n.jpg?_nc_ht=scontent-ort2-1.cdninstagram.com&_nc_cat=1&oh=cc9b10cf211047ac94e4c5c3331e9168&oe=5E6BD630",
            "https://scontent-ort2-1.cdninstagram.com/v/t51.2885-15/e35/p1080x1080/72951344_156972705556133_2319499399644583246_n.jpg?_nc_ht=scontent-ort2-1.cdninstagram.com&_nc_cat=1&oh=39bf38a545941b65de7c88cb3616a1e4&oe=5E7A383C"
        ],
        "likes": 5296394,
        "caption": "swipe for cuteness ☺️👼🏽👼🏽"
    },
    {
        "key": "https://www.instagram.com/p/B5Tr__KnLAq/",
        "datetime": "2019-11-25T23:55:45.000Z",
        "img_urls": [
            "https://scontent-ort2-1.cdninstagram.com/v/t51.2885-15/e35/p1080x1080/75330244_1011083155910149_6665994245569104278_n.jpg?_nc_ht=scontent-ort2-1.cdninstagram.com&_nc_cat=1&oh=fe976d8b21a91e4c5a9406cef2d34b8d&oe=5E759BE0"
        ],
        "likes": 4922708,
        "caption": "throwback bts of my Holiday Collection shoot 💗"
    },
    {
        "key": "https://www.instagram.com/p/B5TcuVpH9tW/",
        "datetime": "2019-11-25T21:42:17.000Z",
        "img_urls": [
            "https://scontent-ort2-1.cdninstagram.com/v/t51.2885-15/e35/s1080x1080/75595366_1265593706958746_920876559104115334_n.jpg?_nc_ht=scontent-ort2-1.cdninstagram.com&_nc_cat=1&oh=67a12b15355ee47f005302be48d75afe&oe=5E8A75DF"
        ],
        "likes": 1671446
    },
    {
        "key": "https://www.instagram.com/p/B5TX5ZGn13O/",
        "datetime": "2019-11-25T21:00:06.000Z",
        "img_urls": [
            "https://scontent-ort2-1.cdninstagram.com/v/t51.2885-15/e35/p1080x1080/72546802_529094877645813_4363696843167988355_n.jpg?_nc_ht=scontent-ort2-1.cdninstagram.com&_nc_cat=1&oh=8c60b775c5b8bdac4c96283eec40e609&oe=5E79CA17",
            "https://scontent-ort2-1.cdninstagram.com/v/t51.2885-15/e35/p1080x1080/75025966_554480118446764_3007148051671916515_n.jpg?_nc_ht=scontent-ort2-1.cdninstagram.com&_nc_cat=1&oh=40461c583122f1fffa267c19fc8b06d4&oe=5E6F78E8"
        ],
        "likes": 6246946,
        "caption": "u get the best of me"
    },
    {
        "key": "https://www.instagram.com/p/B5QgZmtnbPm/",
        "datetime": "2019-11-24T18:16:41.000Z",
        "img_urls": [
            "https://scontent-ort2-1.cdninstagram.com/v/t51.2885-15/e35/s1080x1080/73387397_112617880003548_3010769081604997059_n.jpg?_nc_ht=scontent-ort2-1.cdninstagram.com&_nc_cat=1&oh=34c9dc5ebfac9796bc83af39e37cb7aa&oe=5E85BAAF"
        ],
        "likes": 3603733,
        "caption": "mood. caption this 👀👀"
    },
    {
        "key": "https://www.instagram.com/p/B5OGeQqHngt/",
        "datetime": "2019-11-23T19:51:38.000Z",
        "img_urls": [
            "https://scontent-ort2-1.cdninstagram.com/v/t51.2885-15/e35/p1080x1080/74634307_553070068609371_3107476646810129748_n.jpg?_nc_ht=scontent-ort2-1.cdninstagram.com&_nc_cat=1&oh=93d9a10066bd48fc47f55e0178b557a3&oe=5E768DE9",
            "https://scontent-ort2-1.cdninstagram.com/v/t51.2885-15/e35/p1080x1080/74627677_119131702595991_330372923006270380_n.jpg?_nc_ht=scontent-ort2-1.cdninstagram.com&_nc_cat=1&oh=c736b5567cbe38d302e24c28c7570088&oe=5E85B784"
        ],
        "likes": 7285548,
        "caption": "chill saturdays @ the office in @suspiciousantwerp .. love you guys #ad",
        "hashtags": [
            "ad"
        ]
    },
    {
        "key": "https://www.instagram.com/p/B5LubXDHkQM/",
        "datetime": "2019-11-22T21:43:03.000Z",
        "img_urls": [
            "https://scontent-ort2-1.cdninstagram.com/v/t51.2885-15/e35/p1080x1080/72924373_2428696630732236_3641308777125131293_n.jpg?_nc_ht=scontent-ort2-1.cdninstagram.com&_nc_cat=1&oh=a034af5d428b7fa00f7cd531df9b5ee7&oe=5E7EA7B1"
        ],
        "likes": 6799735,
        "caption": "coolest girl i know 💗"
    },
    {
        "key": "https://www.instagram.com/p/B5JGVUZnoXP/",
        "datetime": "2019-11-21T21:14:13.000Z",
        "img_urls": [
            "https://scontent-ort2-1.cdninstagram.com/v/t51.2885-15/e35/p1080x1080/72277637_2664688300287722_3559378290404475479_n.jpg?_nc_ht=scontent-ort2-1.cdninstagram.com&_nc_cat=1&oh=2326065738a6927e67e9cda4a058a66a&oe=5E65BA5A"
        ],
        "likes": 1128508,
        "caption": "Brb .. hiding these in my vending machines 🤫"
    },
    {
        "key": "https://www.instagram.com/p/B5EIbxqnbqw/",
        "datetime": "2019-11-19T22:56:22.000Z",
        "img_urls": [
            "https://scontent-ort2-1.cdninstagram.com/v/t51.2885-15/e35/s1080x1080/74665231_113821856536142_8914839363968546416_n.jpg?_nc_ht=scontent-ort2-1.cdninstagram.com&_nc_cat=1&oh=5b3f1e61fbb9259e71dfe8a17f6b594c&oe=5E6B621F",
            "https://scontent-ort2-1.cdninstagram.com/v/t51.2885-15/e35/s1080x1080/71028364_151879649504096_9147590399308086821_n.jpg?_nc_ht=scontent-ort2-1.cdninstagram.com&_nc_cat=108&oh=30241449302de370137b8b6a2731e628&oe=5E714CDA"
        ],
        "likes": 3174444,
        "caption": "Just 5 minutes until my Holiday Collection launches on KylieCosmetics.com 🎅🏼 with free shipping until 3pm pst Wednesday to celebrate!"
    },
    {
        "key": "https://www.instagram.com/p/B5DyPXen9ag/",
        "datetime": "2019-11-19T19:42:26.000Z",
        "img_urls": [
            "https://scontent-ort2-1.cdninstagram.com/v/t51.2885-15/e35/p1080x1080/71190994_174348537085316_1852997672584099043_n.jpg?_nc_ht=scontent-ort2-1.cdninstagram.com&_nc_cat=1&oh=8483bf716f0ce5b4fc17b8ac8d21ea91&oe=5E873E86"
        ],
        "likes": 3436389,
        "caption": "3 more hours until my biggest collection of the year goes live on KylieCosmetics.com ♥️ we are celebrating by offering free shipping all day long! See u guys at 3pm pst! @kyliecosmetics 💋🎁"
    },
    {
        "key": "https://www.instagram.com/p/B5Bua61Hino/",
        "datetime": "2019-11-19T00:30:35.000Z",
        "img_urls": [
            "https://scontent-ort2-1.cdninstagram.com/v/t51.2885-15/e35/p1080x1080/71559225_109159730400993_7716813366760808371_n.jpg?_nc_ht=scontent-ort2-1.cdninstagram.com&_nc_cat=109&oh=a8dbbb17eb562a4de9001071670a4849&oe=5E7C4AF9",
            "https://scontent-ort2-1.cdninstagram.com/v/t51.2885-15/e35/p1080x1080/74603522_713011025871660_6375064090364466469_n.jpg?_nc_ht=scontent-ort2-1.cdninstagram.com&_nc_cat=100&oh=2e76b216a3a16cf51cdf8a31feabf737&oe=5E81F015",
            "https://scontent-ort2-1.cdninstagram.com/v/t51.2885-15/e35/p1080x1080/73393241_3216146368460073_9035772447100188084_n.jpg?_nc_ht=scontent-ort2-1.cdninstagram.com&_nc_cat=1&oh=c7e45c8c6266a3d9007bd05a249b1e9d&oe=5E80FCBE",
            "https://scontent-ort2-1.cdninstagram.com/v/t51.2885-15/e35/p1080x1080/72601359_101962807898631_7165428818798120842_n.jpg?_nc_ht=scontent-ort2-1.cdninstagram.com&_nc_cat=103&oh=059d69ec5d1ce4ecf3248060798da787&oe=5E8A8BE9"
        ],
        "likes": 3144535,
        "caption": "Pretty much created the most perfect holiday red lipstick 💋♥️😍 my brand new lip kit Naughty List launches tomorrow at 3pm pst along with the rest of the Holiday ‘19 collection! See u there 💋 @kyliecosmetics"
    },
    {
        "key": "https://www.instagram.com/p/B49FEu9HDRO/",
        "datetime": "2019-11-17T05:12:20.000Z",
        "img_urls": [
            "https://scontent-ort2-1.cdninstagram.com/v/t51.2885-15/e35/p1080x1080/74665253_160331255065352_8273259073299892407_n.jpg?_nc_ht=scontent-ort2-1.cdninstagram.com&_nc_cat=1&oh=52367f504847d67fbc69f7f26f5c6285&oe=5E810F58",
            "https://scontent-ort2-1.cdninstagram.com/v/t51.2885-15/e35/p1080x1080/73407394_951228701911793_8133718090135840981_n.jpg?_nc_ht=scontent-ort2-1.cdninstagram.com&_nc_cat=1&oh=bd3977678140f295c9eb6326afafc9fb&oe=5E7443D1"
        ],
        "likes": 5368758,
        "caption": "naughty list on the lips 💋"
    },
    {
        "key": "https://www.instagram.com/p/B47ub-Gn_Jf/",
        "datetime": "2019-11-16T16:35:17.000Z",
        "img_urls": [
            "https://scontent-ort2-1.cdninstagram.com/v/t51.2885-15/e35/p1080x1080/73524889_2455852594513409_2301084546991673748_n.jpg?_nc_ht=scontent-ort2-1.cdninstagram.com&_nc_cat=105&oh=b9b842e0f023533112d5a6e5671f7e70&oe=5E75651C",
            "https://scontent-ort2-1.cdninstagram.com/v/t51.2885-15/e35/p1080x1080/73554133_1363926243780031_4742754446968342358_n.jpg?_nc_ht=scontent-ort2-1.cdninstagram.com&_nc_cat=1&oh=23fe8db7d7c3700b953fa2a9b4e040e0&oe=5E74E9AC",
            "https://scontent-ort2-1.cdninstagram.com/v/t51.2885-15/e35/p1080x1080/72257107_426023901645011_5564927865292515547_n.jpg?_nc_ht=scontent-ort2-1.cdninstagram.com&_nc_cat=1&oh=87ac1b8508b0cae25f4e946c98afcd57&oe=5E7C166D"
        ],
        "likes": 3856316,
        "caption": "All i want for XMAS is YOU 🎅🏼♥️ my Holiday ‘19 exclusive collection launches November 19th at 3pm pst only on KylieCosmetics.com! .. and to celebrate all domestic and international orders will get free shipping on that day only! See you there 💋"
    },
    {
        "key": "https://www.instagram.com/p/B45o0yHnZcG/",
        "datetime": "2019-11-15T21:07:46.000Z",
        "img_urls": [
            "https://scontent-ort2-1.cdninstagram.com/v/t51.2885-15/e35/p1080x1080/75602182_2679702382069683_476053034522177674_n.jpg?_nc_ht=scontent-ort2-1.cdninstagram.com&_nc_cat=1&oh=dc8c703121035f5dacd950ca483bbca0&oe=5E84921B"
        ],
        "likes": 3689178,
        "caption": "Finally revealing my Holiday ‘19 collection right now on my stories ♥️🎅🏼 this exclusive collection launches Nov.19th at 3pm only on KylieCosmetics.com! Mark this off your XMAS list & don’t be late 💋"
    }
]